mdict_rs-0.1.0.dist-info/METADATA
mdict_rs-0.1.0.dist-info/WHEEL
mdict_rs/__init__.py
mdict_rs/mdict_rs.cpython-313-darwin.so
mdict_rs-0.1.0.dist-info/RECORD
