Metadata-Version: 2.4
Name: mdict-rs
Version: 0.1.0
Classifier: Development Status :: 4 - Beta
Classifier: Intended Audience :: Developers
Classifier: License :: OSI Approved :: MIT License
Classifier: Programming Language :: Python :: 3
Classifier: Programming Language :: Python :: 3.8
Classifier: Programming Language :: Python :: 3.9
Classifier: Programming Language :: Python :: 3.10
Classifier: Programming Language :: Python :: 3.11
Classifier: Programming Language :: Python :: 3.12
Classifier: Programming Language :: Rust
Classifier: Topic :: Software Development :: Libraries :: Python Modules
Classifier: Topic :: Text Processing :: Linguistic
Summary: Python bindings for mdict-rs: A fast MDict dictionary format parser
Keywords: mdict,dictionary,parser,rust,pyo3
Author: zhimoe
License: MIT
Requires-Python: >=3.8
Project-URL: Repository, https://github.com/zhimoe/mdict-rs-py
